envuitest/__init__.py
envuitest/env_msapi.py
envuitest/grid.py
envuitest/pandas_compare.py
envuitest/salesforce.py
envuitest/utils.py
envuitest-0.0.15.dist-info/LICENSE
envuitest-0.0.15.dist-info/METADATA
envuitest-0.0.15.dist-info/WHEEL
envuitest-0.0.15.dist-info/top_level.txt
envuitest-0.0.15.dist-info/RECORD
